superblocks_types/__init__.py
superblocks_types/agent/__init__.py
superblocks_types/agent/v1/__init__.py
superblocks_types/agent/v1/service_pb2.py
superblocks_types/agent/v1/service_pb2_grpc.py
superblocks_types/ai/__init__.py
superblocks_types/ai/v1/__init__.py
superblocks_types/ai/v1/ai_pb2.py
superblocks_types/ai/v1/ai_pb2_grpc.py
superblocks_types/ai/v1/metadata_pb2.py
superblocks_types/ai/v1/metadata_pb2_grpc.py
superblocks_types/ai/v1/service_pb2.py
superblocks_types/ai/v1/service_pb2_grpc.py
superblocks_types/ai/v1/vector_pb2.py
superblocks_types/ai/v1/vector_pb2_grpc.py
superblocks_types/api/__init__.py
superblocks_types/api/v1/__init__.py
superblocks_types/api/v1/api_pb2.py
superblocks_types/api/v1/api_pb2_grpc.py
superblocks_types/api/v1/blocks_pb2.py
superblocks_types/api/v1/blocks_pb2_grpc.py
superblocks_types/api/v1/event_pb2.py
superblocks_types/api/v1/event_pb2_grpc.py
superblocks_types/api/v1/integration_auth_service_pb2.py
superblocks_types/api/v1/integration_auth_service_pb2_grpc.py
superblocks_types/api/v1/requests_pb2.py
superblocks_types/api/v1/requests_pb2_grpc.py
superblocks_types/api/v1/service_pb2.py
superblocks_types/api/v1/service_pb2_grpc.py
superblocks_types/auth/__init__.py
superblocks_types/auth/v1/__init__.py
superblocks_types/auth/v1/auth_pb2.py
superblocks_types/auth/v1/auth_pb2_grpc.py
superblocks_types/buf/__init__.py
superblocks_types/buf/validate/__init__.py
superblocks_types/buf/validate/expression_pb2.py
superblocks_types/buf/validate/expression_pb2_grpc.py
superblocks_types/buf/validate/validate_pb2.py
superblocks_types/buf/validate/validate_pb2_grpc.py
superblocks_types/buf/validate/priv/__init__.py
superblocks_types/buf/validate/priv/private_pb2.py
superblocks_types/buf/validate/priv/private_pb2_grpc.py
superblocks_types/cache/__init__.py
superblocks_types/cache/v1/__init__.py
superblocks_types/cache/v1/cache_pb2.py
superblocks_types/cache/v1/cache_pb2_grpc.py
superblocks_types/common/__init__.py
superblocks_types-0.0.14.dist-info/METADATA
superblocks_types-0.0.14.dist-info/WHEEL
superblocks_types-0.0.14.dist-info/top_level.txt
superblocks_types-0.0.14.dist-info/RECORD
