Metadata-Version: 2.1
Name: superblocks-types
Version: 0.0.14
Summary: Superblocks Official Python Types
Home-page: https://github.com/superblocksteam/types
Author: Superblocks
License: MIT
Keywords: superblocks types
Requires-Python: >=3.10
